azure/functions_parser/__init__.py
azure_functions_parser-0.0.1.dist-info/METADATA
azure_functions_parser-0.0.1.dist-info/WHEEL
azure_functions_parser-0.0.1.dist-info/licenses/LICENSE
azure_functions_parser-0.0.1.dist-info/RECORD
